helpo/__init__.py
helpo/aws_general.py
helpo/check_env_vars.py
helpo/dataframe_tools.py
helpo/dynamic_loader.py
helpo/file_tools.py
helpo/hcollections.py
helpo/hdatetime.py
helpo/hfile.py
helpo/hstrops.py
helpo/hsubprocess.py
helpo/old/data_structure_search.py
helpo/old/os_functions.py
helpo/plotter_tools.py
helpohelpo-0.5.0.dist-info/LICENSE
helpohelpo-0.5.0.dist-info/METADATA
helpohelpo-0.5.0.dist-info/WHEEL
helpohelpo-0.5.0.dist-info/RECORD
