Metadata-Version: 2.1
Name: helpohelpo
Version: 0.5.0
Summary: A library of python helpers
License: LICENSE
Keywords: python3,helpers
Author: Stablecaps
Author-email: 114529342+darkpandarts@users.noreply.github.com
Requires-Python: >=3.9,<4.0
Classifier: License :: OSI Approved :: MIT License
Classifier: License :: Other/Proprietary License
Classifier: Operating System :: OS Independent
Classifier: Programming Language :: Python :: 3
Classifier: Programming Language :: Python :: 3.9
Classifier: Programming Language :: Python :: 3.10
Classifier: Programming Language :: Python :: 3.11
Classifier: Programming Language :: Python :: 3.12
Requires-Dist: arrow (>=1.3.0,<2.0.0)
Requires-Dist: dotmap (>=1.3.30,<2.0.0)
Requires-Dist: pydash (>=7.0.6,<8.0.0)
Requires-Dist: pytest-cov (>=4.1.0,<5.0.0)
Requires-Dist: python-semantic-release (>=8.7.0,<9.0.0)
Requires-Dist: ruamel-yaml (>=0.18.5,<0.19.0)
Project-URL: Bug Tracker, https://github.com/stablecaps/helpohelpo/issues
Project-URL: Homepage, https://github.com/stablecaps/helpohelpo
